mainframe/__init__.py
mainframe/array_type.py
mainframe/button_component.py
mainframe/child_component.py
mainframe/client.py
mainframe/component.py
mainframe/form_component.py
mainframe/media_component.py
mainframe/response.py
mainframe/root_component.py
mainframe/text_component.py
mainframe_bot_api-1.3.5.dist-info/DESCRIPTION.rst
mainframe_bot_api-1.3.5.dist-info/METADATA
mainframe_bot_api-1.3.5.dist-info/RECORD
mainframe_bot_api-1.3.5.dist-info/WHEEL
mainframe_bot_api-1.3.5.dist-info/metadata.json
mainframe_bot_api-1.3.5.dist-info/top_level.txt
